fastapi_rtk/__init__.py
fastapi_rtk/_version.py
fastapi_rtk/apis.py
fastapi_rtk/config.py
fastapi_rtk/const.py
fastapi_rtk/db.py
fastapi_rtk/decorators.py
fastapi_rtk/dependencies.py
fastapi_rtk/exceptions.py
fastapi_rtk/fastapi_react_toolkit.py
fastapi_rtk/filters.py
fastapi_rtk/globals.py
fastapi_rtk/manager.py
fastapi_rtk/middlewares.py
fastapi_rtk/mixins.py
fastapi_rtk/models.py
fastapi_rtk/routers.py
fastapi_rtk/schemas.py
fastapi_rtk/setting.py
fastapi_rtk/types.py
fastapi_rtk/version.py
fastapi_rtk/api/__init__.py
fastapi_rtk/api/base_api.py
fastapi_rtk/api/model_rest_api.py
fastapi_rtk/auth/__init__.py
fastapi_rtk/auth/auth.py
fastapi_rtk/auth/hashers/__init__.py
fastapi_rtk/auth/hashers/pbkdf2.py
fastapi_rtk/auth/hashers/scrypt.py
fastapi_rtk/auth/password_helpers/__init__.py
fastapi_rtk/auth/password_helpers/fab.py
fastapi_rtk/auth/strategies/__init__.py
fastapi_rtk/auth/strategies/config.py
fastapi_rtk/auth/strategies/db.py
fastapi_rtk/auth/strategies/jwt.py
fastapi_rtk/backends/__init__.py
fastapi_rtk/backends/generic/__init__.py
fastapi_rtk/backends/generic/column.py
fastapi_rtk/backends/generic/db.py
fastapi_rtk/backends/generic/exceptions.py
fastapi_rtk/backends/generic/filters.py
fastapi_rtk/backends/generic/interface.py
fastapi_rtk/backends/generic/model.py
fastapi_rtk/backends/generic/session.py
fastapi_rtk/backends/sqla/__init__.py
fastapi_rtk/backends/sqla/column.py
fastapi_rtk/backends/sqla/db.py
fastapi_rtk/backends/sqla/exceptions.py
fastapi_rtk/backends/sqla/filters.py
fastapi_rtk/backends/sqla/interface.py
fastapi_rtk/backends/sqla/model.py
fastapi_rtk/backends/sqla/session.py
fastapi_rtk/backends/sqla/extensions/__init__.py
fastapi_rtk/backends/sqla/extensions/audit/__init__.py
fastapi_rtk/backends/sqla/extensions/audit/audit.py
fastapi_rtk/backends/sqla/extensions/audit/types.py
fastapi_rtk/backends/sqla/extensions/geoalchemy2/__init__.py
fastapi_rtk/backends/sqla/extensions/geoalchemy2/filters.py
fastapi_rtk-1.0.23.dist-info/METADATA
fastapi_rtk-1.0.23.dist-info/WHEEL
fastapi_rtk-1.0.23.dist-info/entry_points.txt
fastapi_rtk-1.0.23.dist-info/licenses/LICENSE
fastapi_rtk-1.0.23.dist-info/RECORD
