Metadata-Version: 2.4
Name: fastapi-rtk
Version: 1.0.23
Summary: A package that provides a set of tools to build a FastAPI application with a Class-Based CRUD API.
Project-URL: Homepage, https://codeberg.org/datatactics/fastapi-rtk
Project-URL: Issues, https://codeberg.org/datatactics/fastapi-rtk/issues
Author-email: Matthias Leinweber <m.leinweber@datatactics.de>, Agustinus Nicander Hery <a.hery@datatactics.de>
License-File: LICENSE
Classifier: Development Status :: 4 - Beta
Classifier: Intended Audience :: Developers
Classifier: Programming Language :: Python :: 3.10
Classifier: Programming Language :: Python :: 3.11
Classifier: Programming Language :: Python :: 3.12
Classifier: Programming Language :: Python :: 3.13
Classifier: Topic :: Software Development :: Libraries :: Application Frameworks
Requires-Python: >=3.10
Requires-Dist: alembic>=1.17.0
Requires-Dist: beautifulsoup4>=4.14.2
Requires-Dist: fastapi-babel>=1.0.0
Requires-Dist: fastapi-users[oauth,sqlalchemy]>=15.0.3
Requires-Dist: fastapi[standard]>=0.119.1
Requires-Dist: jsonschema2md>=1.7.0
Requires-Dist: marshmallow-sqlalchemy>=1.4.2
Requires-Dist: polib>=1.2.0
Requires-Dist: prometheus-fastapi-instrumentator>=7.1.0
Requires-Dist: secweb>=1.25.2
Requires-Dist: sqlalchemy-utils>=0.42.0
Requires-Dist: uvicorn==0.38.0
Requires-Dist: werkzeug>=3.1.5
